blaster/__init__.py
blaster/blast.py
blaster/constants.py
blaster/core.py
blaster/metadata.py
examples/__init__.py
examples/build_houses_parallel.py
examples/build_houses_serial.py
examples/house.py
tests/__init__.py
tests/test_blast.py
tests/test_core.py
tests/test_engine_parallel.py
tests/test_engine_serial.py
tests/examples/__init__.py
tests/examples/invalid.py
tests/examples/valid.py
blaster-0.6.0.dist-info/LICENSE
blaster-0.6.0.dist-info/METADATA
blaster-0.6.0.dist-info/WHEEL
blaster-0.6.0.dist-info/top_level.txt
blaster-0.6.0.dist-info/RECORD
