Metadata-Version: 2.1
Name: blaster
Version: 0.6.0
Summary: Blast off a list of tasks calling each tasks methods defined
Home-page: https://github.com/ryankwilliams/blaster
Author: Ryan Williams
License: GPLv3
Classifier: License :: OSI Approved :: GNU General Public License v3 (GPLv3)
Classifier: Programming Language :: Python :: 3
Classifier: Programming Language :: Python :: Implementation :: CPython
Classifier: Topic :: Software Development :: Libraries :: Python Modules
Requires-Python: >=3.9
License-File: LICENSE
